np_lims_tk/__init__.py
np_lims_tk/config.py
np_lims_tk/core.py
np_lims_tk/exceptions.py
np_lims_tk/local_paths.py
np_lims_tk/models.py
np_lims_tk/queries.py
np_lims_tk/utils.py
np_lims_tk/wkft.py
np_lims_tk-0.9.2.dist-info/LICENSE
np_lims_tk-0.9.2.dist-info/WHEEL
np_lims_tk-0.9.2.dist-info/METADATA
np_lims_tk-0.9.2.dist-info/RECORD
