Metadata-Version: 2.1
Name: np-lims-tk
Version: 0.9.2
Summary: Awesome `np-lims-tk` is a Python cli/package created with https://github.com/TezRomacH/python-package-template
Home-page: https://github.com/np_lims_tk/np-lims-tk
License: MIT
Author: np-lims-tk
Author-email: chrism@alleninstitute.org
Requires-Python: >=3.9,<4.0
Classifier: Development Status :: 3 - Alpha
Classifier: Intended Audience :: Developers
Classifier: License :: OSI Approved :: MIT License
Classifier: Operating System :: OS Independent
Classifier: Programming Language :: Python :: 3
Classifier: Programming Language :: Python :: 3.10
Classifier: Programming Language :: Python :: 3.7
Classifier: Programming Language :: Python :: 3.8
Classifier: Programming Language :: Python :: 3.9
Classifier: Topic :: Software Development :: Libraries :: Python Modules
Requires-Dist: PyYAML (==6.0)
Requires-Dist: importlib_metadata (>=4.5.0,<5.0.0); python_version < "3.8"
Requires-Dist: mongomock (>=4.1.2,<5.0.0)
Requires-Dist: psycopg2 (>=2.9.3,<3.0.0)
Requires-Dist: pymongo (>=4.2.0,<5.0.0)
Requires-Dist: rich (==12.5.1)
Requires-Dist: typer (==0.6.1)
Project-URL: Repository, https://github.com/np_lims_tk/np-lims-tk
